flowiz/__init__.py
flowiz/__main__.py
flowiz/flowiz.py
flowiz/gui/__init__.py
flowiz/gui/__main__.py
flowiz/gui/index.py
flowiz/gui/web/index.html
flowiz/gui/web/assets/flowiz-logo.png
flowiz/gui/web/assets/flowiz.png
flowiz/gui/web/assets/rgb.jpg
flowiz/gui/web/assets/uv.jpg
flowiz/gui/web/css/dropzone.css
flowiz/gui/web/css/materialize.css
flowiz/gui/web/css/materialize.min.css
flowiz/gui/web/css/style.css
flowiz/gui/web/fonts/material_icons.woff2
flowiz/gui/web/guitemp/frame_0003.flo.png
flowiz/gui/web/guitemp/frame_0003.flo.u.png
flowiz/gui/web/guitemp/frame_0003.flo.v.png
flowiz/gui/web/guitemp/frame_0004.flo.png
flowiz/gui/web/guitemp/frame_0004.flo.u.png
flowiz/gui/web/guitemp/frame_0004.flo.v.png
flowiz/gui/web/guitemp/index.html
flowiz/gui/web/js/dropzone.js
flowiz/gui/web/js/materialize.js
flowiz/gui/web/js/script.js
flowiz/gui/web/mockup/frame_0001.flo.png
flowiz/gui/web/mockup/frame_0001.flo.u.png
flowiz/gui/web/mockup/frame_0001.flo.v.png
flowiz/gui/web/mockup/frame_0002.flo.png
flowiz/gui/web/mockup/frame_0002.flo.u.png
flowiz/gui/web/mockup/frame_0002.flo.v.png
flowiz/gui/web/mockup/frame_0003.flo.png
flowiz/gui/web/mockup/frame_0003.flo.u.png
flowiz/gui/web/mockup/frame_0003.flo.v.png
flowiz/gui/web/mockup/frame_0004.flo.png
flowiz/gui/web/mockup/frame_0004.flo.u.png
flowiz/gui/web/mockup/frame_0004.flo.v.png
flowiz/gui/web/mockup/frame_0005.flo.png
flowiz/gui/web/mockup/frame_0005.flo.u.png
flowiz/gui/web/mockup/frame_0005.flo.v.png
flowiz/gui/web/mockup/index.html
flowiz-2.4.0.dist-info/LICENSE
flowiz-2.4.0.dist-info/METADATA
flowiz-2.4.0.dist-info/WHEEL
flowiz-2.4.0.dist-info/top_level.txt
flowiz-2.4.0.dist-info/RECORD
