Metadata-Version: 2.1
Name: flowiz
Version: 2.4.0
Summary: Optical Flow file wizard
Home-page: https://github.com/georgegach/flowiz
Author: George Gach
Author-email: georgegach@outlook.com
License: UNKNOWN
Platform: UNKNOWN
Classifier: Programming Language :: Python :: 3
Classifier: License :: OSI Approved :: MIT License
Classifier: Operating System :: OS Independent
Requires-Dist: numpy
Requires-Dist: tqdm
Requires-Dist: matplotlib
Requires-Dist: eel
